{
  "_meta": {
    "hero": "Arbalester",
    "skill_count": 3
  },
  "skills": {
    "4301": {
      "Id": 4301,
      "Revision": 0,
      "Name": {
        "Key": "l10n:skill/name?id=4301#static",
        "DefaultValue": "Clean Shot",
        "HasBreakSymbol": false
      },
      "Description": {
        "Key": "l10n:skill/description?id=4301#static",
        "DefaultValue": "Attacks a single enemy. Has a 25% chance to transfer 1 random debuff from this Champion to the enemy.",
        "HasBreakSymbol": false
      },
      "Group": "Active",
      "Targets": "Producer",
      "Cooldown": 0,
      "ReduceCooldownProhibited": false,
      "IncreaseCooldownProhibited": false,
      "CooldownIncludeProducer": false,
      "IsSecret": false,
      "ShowDamageScale": true,
      "Visibility": "Visible",
      "SkillLevelBonuses": [
        {
          "SkillBonusType": "Attack",
          "Value": 0.05
        },
        {
          "SkillBonusType": "Attack",
          "Value": 0.05
        },
        {
          "SkillBonusType": "EffectChance",
          "Value": 0.1
        },
        {
          "SkillBonusType": "EffectChance",
          "Value": 0.15
        }
      ],
      "Effects": [
        {
          "Count": 1,
          "Id": 43011,
          "KindId": "Damage",
          "Group": "Active",
          "TargetParams": {
            "TargetType": "Target",
            "Exclusive": false,
            "FirstHitInSelected": false,
            "TakeOneRandom": false,
            "NotAoeDamage": false
          },
          "IsEffectDescription": false,
          "ConsidersDead": false,
          "LeaveThroughDeath": false,
          "DoesntSetSkillOnCooldown": false,
          "IgnoresCooldown": false,
          "IsUnique": false,
          "IterationChanceRolling": false,
          "StackCount": 1,
          "MultiplierFormula": "3.3*ATK",
          "CalcMultiplier": {
            "method_ptr": "<IntPtr>",
            "invoke_impl": "<IntPtr>",
            "m_target": {},
            "method": "<IntPtr>",
            "delegate_trampoline": "<IntPtr>",
            "extra_arg": "<IntPtr>",
            "method_code": "<IntPtr>",
            "interp_method": "<IntPtr>",
            "interp_invoke_impl": "<IntPtr>",
            "method_info": "<MethodInfo>",
            "method_is_virtual": false,
            "Method": "<MethodInfo>",
            "Target": {}
          },
          "PersistsThroughRounds": false,
          "SnapshotRequired": false,
          "MultiplierNotEvaluatedByAI": false,
          "TargetType": "Target",
          "StatusEffectFamily": "43010",
          "Category": "Damage",
          "IsContainer": false,
          "IsGuaranteed": true,
          "IsResistable": false,
          "IsExtraTurnEffect": false,
          "IsDamageModifiactionEffect": false,
          "IsEvadeOrBlocker": false,
          "IsActive": true,
          "IsRelative": false,
          "HasMultiplier": true,
          "CanStack": false,
          "IsPassiveBonus": false,
          "CanApplyOnCorpse": false,
          "ConsidersBanished": false,
          "SharedModel.Battle.AI.IAiEffect.TypeId": 43011,
          "SharedModel.Battle.AI.IAiEffect.KindId": "Damage",
          "SharedModel.Battle.AI.IAiEffect.TargetType": "Target",
          "SharedModel.Battle.AI.IAiEffect.MultiplierFormula": "3.3*ATK",
          "SharedModel.Battle.AI.IAiEffect.IsRelative": false,
          "SharedModel.Battle.AI.IAiEffect.MultiplierNotEvaluatedByAI": false,
          "SharedModel.Battle.AI.IAiEffect.Count": 1,
          "SharedModel.Battle.AI.IAiEffect.TargetParams": {
            "TargetType": "Target",
            "Exclusive": false,
            "FirstHitInSelected": false,
            "TakeOneRandom": false,
            "NotAoeDamage": false
          },
          "RealEffect": "<EffectType>"
        },
        {
          "Count": 1,
          "Id": 43012,
          "KindId": "TransferDebuff",
          "Group": "Active",
          "TargetParams": {
            "TargetType": "RelationTarget",
            "Exclusive": false,
            "FirstHitInSelected": false,
            "TakeOneRandom": false,
            "NotAoeDamage": false
          },
          "IsEffectDescription": false,
          "ConsidersDead": false,
          "LeaveThroughDeath": false,
          "DoesntSetSkillOnCooldown": false,
          "IgnoresCooldown": false,
          "IsUnique": false,
          "IterationChanceRolling": false,
          "Relation": {
            "EffectTypeId": 0,
            "Phases": [
              "AfterDamageDealt"
            ],
            "ActivateOnGlancingHit": false
          },
          "Chance": {
            "HasValue": false,
            "hasValue": false,
            "value": 527.695
          },
          "StackCount": 1,
          "PersistsThroughRounds": false,
          "SnapshotRequired": false,
          "TransferDebuffParams": {
            "Count": 1,
            "UnapplyMode": "Selected",
            "IncludeProducer": false,
            "RemoveFrom": "Producer",
            "ApplyTo": "Target"
          },
          "MultiplierNotEvaluatedByAI": false,
          "TargetType": "RelationTarget",
          "StatusEffectFamily": "43010",
          "Category": "InstantBuff",
          "IsContainer": false,
          "IsGuaranteed": false,
          "IsResistable": false,
          "IsExtraTurnEffect": false,
          "IsDamageModifiactionEffect": false,
          "IsEvadeOrBlocker": false,
          "IsActive": true,
          "IsRelative": true,
          "HasMultiplier": false,
          "CanStack": false,
          "IsPassiveBonus": false,
          "CanApplyOnCorpse": false,
          "ConsidersBanished": false,
          "SharedModel.Battle.AI.IAiEffect.TypeId": 43012,
          "SharedModel.Battle.AI.IAiEffect.KindId": "TransferDebuff",
          "SharedModel.Battle.AI.IAiEffect.TargetType": "RelationTarget",
          "SharedModel.Battle.AI.IAiEffect.IsRelative": true,
          "SharedModel.Battle.AI.IAiEffect.MultiplierNotEvaluatedByAI": false,
          "SharedModel.Battle.AI.IAiEffect.Count": 1,
          "SharedModel.Battle.AI.IAiEffect.TransferDebuffParams": {
            "Count": 1,
            "UnapplyMode": "Selected",
            "IncludeProducer": false,
            "RemoveFrom": "Producer",
            "ApplyTo": "Target"
          },
          "SharedModel.Battle.AI.IAiEffect.TargetParams": {
            "TargetType": "RelationTarget",
            "Exclusive": false,
            "FirstHitInSelected": false,
            "TakeOneRandom": false,
            "NotAoeDamage": false
          },
          "RealEffect": "<EffectType>"
        }
      ],
      "VisualSkillDuration": {
        "HasValue": false,
        "hasValue": false,
        "value": 527.695
      },
      "IsHiddenOnHud": false,
      "IsVisibleForAI": true,
      "LevelBonuses": [
        {
          "SkillBonusType": "Attack",
          "Value": 0.05
        },
        {
          "SkillBonusType": "Attack",
          "Value": 0.05
        },
        {
          "SkillBonusType": "EffectChance",
          "Value": 0.1
        },
        {
          "SkillBonusType": "EffectChance",
          "Value": 0.15
        }
      ],
      "IsDefault": true,
      "MaxLevel": 5,
      "IsActive": true,
      "IsWarlordSkill": false,
      "IgnoresTaunt": false
    },
    "4302": {
      "Id": 4302,
      "Revision": 0,
      "Name": {
        "Key": "l10n:skill/name?id=4302#static",
        "DefaultValue": "Despair",
        "HasBreakSymbol": false
      },
      "Description": {
        "Key": "l10n:skill/description?id=4302#static",
        "DefaultValue": "Attacks a single enemy. Puts the target's skills on cooldown with 60% chance.",
        "HasBreakSymbol": false
      },
      "Group": "Active",
      "Targets": "Producer",
      "Cooldown": 4,
      "ReduceCooldownProhibited": false,
      "IncreaseCooldownProhibited": false,
      "CooldownIncludeProducer": false,
      "IsSecret": false,
      "ShowDamageScale": true,
      "Visibility": "Visible",
      "SkillLevelBonuses": [
        {
          "SkillBonusType": "Attack",
          "Value": 0.1
        },
        {
          "SkillBonusType": "EffectChance",
          "Value": 0.1
        },
        {
          "SkillBonusType": "EffectChance",
          "Value": 0.1
        },
        {
          "SkillBonusType": "EffectChance",
          "Value": 0.1
        },
        {
          "SkillBonusType": "EffectChance",
          "Value": 0.1
        }
      ],
      "Effects": [
        {
          "Count": 1,
          "Id": 43021,
          "KindId": "Damage",
          "Group": "Active",
          "TargetParams": {
            "TargetType": "Target",
            "Exclusive": false,
            "FirstHitInSelected": false,
            "TakeOneRandom": false,
            "NotAoeDamage": false
          },
          "IsEffectDescription": false,
          "ConsidersDead": false,
          "LeaveThroughDeath": false,
          "DoesntSetSkillOnCooldown": false,
          "IgnoresCooldown": false,
          "IsUnique": false,
          "IterationChanceRolling": false,
          "StackCount": 1,
          "MultiplierFormula": "5.8*ATK",
          "CalcMultiplier": {
            "method_ptr": "<IntPtr>",
            "invoke_impl": "<IntPtr>",
            "m_target": {},
            "method": "<IntPtr>",
            "delegate_trampoline": "<IntPtr>",
            "extra_arg": "<IntPtr>",
            "method_code": "<IntPtr>",
            "interp_method": "<IntPtr>",
            "interp_invoke_impl": "<IntPtr>",
            "method_info": "<MethodInfo>",
            "method_is_virtual": false,
            "Method": "<MethodInfo>",
            "Target": {}
          },
          "PersistsThroughRounds": false,
          "SnapshotRequired": false,
          "MultiplierNotEvaluatedByAI": false,
          "TargetType": "Target",
          "StatusEffectFamily": "43020",
          "Category": "Damage",
          "IsContainer": false,
          "IsGuaranteed": true,
          "IsResistable": false,
          "IsExtraTurnEffect": false,
          "IsDamageModifiactionEffect": false,
          "IsEvadeOrBlocker": false,
          "IsActive": true,
          "IsRelative": false,
          "HasMultiplier": true,
          "CanStack": false,
          "IsPassiveBonus": false,
          "CanApplyOnCorpse": false,
          "ConsidersBanished": false,
          "SharedModel.Battle.AI.IAiEffect.TypeId": 43021,
          "SharedModel.Battle.AI.IAiEffect.KindId": "Damage",
          "SharedModel.Battle.AI.IAiEffect.TargetType": "Target",
          "SharedModel.Battle.AI.IAiEffect.MultiplierFormula": "5.8*ATK",
          "SharedModel.Battle.AI.IAiEffect.IsRelative": false,
          "SharedModel.Battle.AI.IAiEffect.MultiplierNotEvaluatedByAI": false,
          "SharedModel.Battle.AI.IAiEffect.Count": 1,
          "SharedModel.Battle.AI.IAiEffect.TargetParams": {
            "TargetType": "Target",
            "Exclusive": false,
            "FirstHitInSelected": false,
            "TakeOneRandom": false,
            "NotAoeDamage": false
          },
          "RealEffect": "<EffectType>"
        },
        {
          "Count": 1,
          "Id": 43022,
          "KindId": "IncreaseCooldown",
          "Group": "Active",
          "TargetParams": {
            "TargetType": "RelationTarget",
            "Exclusive": false,
            "FirstHitInSelected": false,
            "TakeOneRandom": false,
            "NotAoeDamage": false
          },
          "IsEffectDescription": false,
          "ConsidersDead": false,
          "LeaveThroughDeath": false,
          "DoesntSetSkillOnCooldown": false,
          "IgnoresCooldown": false,
          "IsUnique": false,
          "IterationChanceRolling": false,
          "Relation": {
            "EffectTypeId": 0,
            "Phases": [
              "AfterDamageDealt"
            ],
            "ActivateOnGlancingHit": false
          },
          "Chance": 529.585,
          "StackCount": 1,
          "PersistsThroughRounds": false,
          "SnapshotRequired": false,
          "ChangeSkillCooldownParams": {
            "Turns": -1,
            "SkillToChange": "All"
          },
          "MultiplierNotEvaluatedByAI": false,
          "TargetType": "RelationTarget",
          "StatusEffectFamily": "43020",
          "Category": "InstantDebuff",
          "IsContainer": false,
          "IsGuaranteed": false,
          "IsResistable": true,
          "IsExtraTurnEffect": false,
          "IsDamageModifiactionEffect": false,
          "IsEvadeOrBlocker": false,
          "IsActive": true,
          "IsRelative": true,
          "HasMultiplier": false,
          "CanStack": false,
          "IsPassiveBonus": false,
          "CanApplyOnCorpse": false,
          "ConsidersBanished": false,
          "SharedModel.Battle.AI.IAiEffect.TypeId": 43022,
          "SharedModel.Battle.AI.IAiEffect.KindId": "IncreaseCooldown",
          "SharedModel.Battle.AI.IAiEffect.TargetType": "RelationTarget",
          "SharedModel.Battle.AI.IAiEffect.IsRelative": true,
          "SharedModel.Battle.AI.IAiEffect.MultiplierNotEvaluatedByAI": false,
          "SharedModel.Battle.AI.IAiEffect.Count": 1,
          "SharedModel.Battle.AI.IAiEffect.ChangeSkillCooldownParams": {
            "Turns": -1,
            "SkillToChange": "All"
          },
          "SharedModel.Battle.AI.IAiEffect.TargetParams": {
            "TargetType": "RelationTarget",
            "Exclusive": false,
            "FirstHitInSelected": false,
            "TakeOneRandom": false,
            "NotAoeDamage": false
          },
          "RealEffect": "<EffectType>"
        }
      ],
      "VisualSkillDuration": {
        "HasValue": false,
        "hasValue": false,
        "value": 527.695
      },
      "IsHiddenOnHud": false,
      "IsVisibleForAI": true,
      "LevelBonuses": [
        {
          "SkillBonusType": "Attack",
          "Value": 0.1
        },
        {
          "SkillBonusType": "EffectChance",
          "Value": 0.1
        },
        {
          "SkillBonusType": "EffectChance",
          "Value": 0.1
        },
        {
          "SkillBonusType": "EffectChance",
          "Value": 0.1
        },
        {
          "SkillBonusType": "EffectChance",
          "Value": 0.1
        }
      ],
      "IsDefault": false,
      "MaxLevel": 6,
      "IsActive": true,
      "IsWarlordSkill": false,
      "IgnoresTaunt": false
    },
    "4303": {
      "Id": 4303,
      "Revision": 0,
      "Name": {
        "Key": "l10n:skill/name?id=4303#static",
        "DefaultValue": "Soulbreak",
        "HasBreakSymbol": false
      },
      "Description": {
        "Key": "l10n:skill/description?id=4303#static",
        "DefaultValue": "Attacks a single enemy. Damage increases according to the number of debuffs on the target.",
        "HasBreakSymbol": false
      },
      "Group": "Active",
      "Targets": "Producer",
      "Cooldown": 6,
      "ReduceCooldownProhibited": false,
      "IncreaseCooldownProhibited": false,
      "CooldownIncludeProducer": false,
      "IsSecret": false,
      "ShowDamageScale": true,
      "Visibility": "Visible",
      "SkillLevelBonuses": [
        {
          "SkillBonusType": "Attack",
          "Value": 0.05
        },
        {
          "SkillBonusType": "Attack",
          "Value": 0.05
        },
        {
          "SkillBonusType": "CooltimeTurn",
          "Value": 1
        }
      ],
      "Effects": [
        {
          "Count": 1,
          "Id": 43031,
          "KindId": "Damage",
          "Group": "Active",
          "TargetParams": {
            "TargetType": "Target",
            "Exclusive": false,
            "FirstHitInSelected": false,
            "TakeOneRandom": false,
            "NotAoeDamage": false
          },
          "IsEffectDescription": false,
          "ConsidersDead": false,
          "LeaveThroughDeath": false,
          "DoesntSetSkillOnCooldown": false,
          "IgnoresCooldown": false,
          "IsUnique": false,
          "IterationChanceRolling": false,
          "StackCount": 1,
          "MultiplierFormula": "ATK*(2+TRG_DEBUFF_COUNT)",
          "CalcMultiplier": {
            "method_ptr": "<IntPtr>",
            "invoke_impl": "<IntPtr>",
            "m_target": {},
            "method": "<IntPtr>",
            "delegate_trampoline": "<IntPtr>",
            "extra_arg": "<IntPtr>",
            "method_code": "<IntPtr>",
            "interp_method": "<IntPtr>",
            "interp_invoke_impl": "<IntPtr>",
            "method_info": "<MethodInfo>",
            "method_is_virtual": false,
            "Method": "<MethodInfo>",
            "Target": {}
          },
          "PersistsThroughRounds": false,
          "SnapshotRequired": false,
          "MultiplierNotEvaluatedByAI": false,
          "TargetType": "Target",
          "StatusEffectFamily": "43030",
          "Category": "Damage",
          "IsContainer": false,
          "IsGuaranteed": true,
          "IsResistable": false,
          "IsExtraTurnEffect": false,
          "IsDamageModifiactionEffect": false,
          "IsEvadeOrBlocker": false,
          "IsActive": true,
          "IsRelative": false,
          "HasMultiplier": true,
          "CanStack": false,
          "IsPassiveBonus": false,
          "CanApplyOnCorpse": false,
          "ConsidersBanished": false,
          "SharedModel.Battle.AI.IAiEffect.TypeId": 43031,
          "SharedModel.Battle.AI.IAiEffect.KindId": "Damage",
          "SharedModel.Battle.AI.IAiEffect.TargetType": "Target",
          "SharedModel.Battle.AI.IAiEffect.MultiplierFormula": "ATK*(2+TRG_DEBUFF_COUNT)",
          "SharedModel.Battle.AI.IAiEffect.IsRelative": false,
          "SharedModel.Battle.AI.IAiEffect.MultiplierNotEvaluatedByAI": false,
          "SharedModel.Battle.AI.IAiEffect.Count": 1,
          "SharedModel.Battle.AI.IAiEffect.TargetParams": {
            "TargetType": "Target",
            "Exclusive": false,
            "FirstHitInSelected": false,
            "TakeOneRandom": false,
            "NotAoeDamage": false
          },
          "RealEffect": "<EffectType>"
        }
      ],
      "VisualSkillDuration": {
        "HasValue": false,
        "hasValue": false,
        "value": 527.695
      },
      "IsHiddenOnHud": false,
      "IsVisibleForAI": true,
      "LevelBonuses": [
        {
          "SkillBonusType": "Attack",
          "Value": 0.05
        },
        {
          "SkillBonusType": "Attack",
          "Value": 0.05
        },
        {
          "SkillBonusType": "CooltimeTurn",
          "Value": 1
        }
      ],
      "IsDefault": false,
      "MaxLevel": 4,
      "IsActive": true,
      "IsWarlordSkill": false,
      "IgnoresTaunt": false
    }
  }
}